[
  {
    "id": 1769601932970,
    "itemType": "pastries",
    "product": "Black Forest",
    "quantity": 2,
    "unitPrice": 80,
    "total": 160,
    "saleType": "Counter Sale",
    "paymentMode": "Cash",
    "date": "2026-01-28T12:05:32.962Z",
    "status": "Completed",
    "addedBy": "sam12",
    "business": "MA-2818"
  },
  {
    "id": 1769623525449,
    "itemType": "savory",
    "product": "Veg Puff",
    "quantity": 4,
    "unitPrice": 35,
    "total": 140,
    "saleType": "Online Order",
    "paymentMode": "UPI",
    "status": "Completed",
    "addedBy": "sam12",
    "business": "MA-2818",
    "date": "2026-01-28T18:05:25.449Z"
  },
  {
    "id": 1769623851817,
    "itemType": "cakes",
    "product": "Butterscotch Cake",
    "quantity": 1,
    "unitPrice": 450,
    "total": 450,
    "saleType": "Online Order",
    "paymentMode": "UPI",
    "status": "Completed",
    "addedBy": "sam12",
    "business": "MA-2818",
    "date": "2026-01-28T18:10:51.817Z"
  },
  {
    "id": 1769623947555,
    "itemType": "cookies",
    "product": "Butter Cookies",
    "quantity": 100,
    "unitPrice": 10,
    "total": 1000,
    "saleType": "Bulk Order",
    "paymentMode": "Card",
    "status": "Completed",
    "addedBy": "sam12",
    "business": "MA-2818",
    "date": "2026-01-28T18:12:27.556Z"
  },
  {
    "id": 1769692934996,
    "itemType": "pastries",
    "product": "Pineapple Pastry",
    "quantity": 5,
    "unitPrice": 70,
    "total": 350,
    "saleType": "Counter Sale",
    "paymentMode": "Cash",
    "status": "Completed",
    "addedBy": "sam12",
    "business": "MA-2818",
    "date": "2026-01-29T13:22:14.996Z"
  },
  {
    "id": 1769693003300,
    "itemType": "savory",
    "product": "Paneer Puff",
    "quantity": 2,
    "unitPrice": 50,
    "total": 100,
    "saleType": "Counter Sale",
    "paymentMode": "Cash",
    "status": "Completed",
    "addedBy": "sam12",
    "business": "MA-2818",
    "date": "2026-01-29T13:23:23.300Z"
  },
  {
    "id": 1769693062794,
    "itemType": "cakes",
    "product": "Red Velvet Cake",
    "quantity": 4,
    "unitPrice": 600,
    "total": 2400,
    "saleType": "Bulk Order",
    "paymentMode": "Card",
    "status": "Completed",
    "addedBy": "sam12",
    "business": "MA-2818",
    "date": "2026-01-29T13:24:22.794Z"
  },
  {
    "id": 1769693191019,
    "itemType": "pastries",
    "product": "Chocolate Muffin",
    "quantity": 6,
    "unitPrice": 30,
    "total": 180,
    "saleType": "Counter Sale",
    "paymentMode": "Cash",
    "status": "Completed",
    "addedBy": "sam12",
    "business": "MA-2818",
    "date": "2026-01-29T13:26:31.019Z"
  },
  {
    "id": 1769693220803,
    "itemType": "breads",
    "product": "Brown Bread",
    "quantity": 2,
    "unitPrice": 45,
    "total": 90,
    "saleType": "Counter Sale",
    "paymentMode": "UPI",
    "status": "Completed",
    "addedBy": "sam12",
    "business": "MA-2818",
    "date": "2026-01-29T13:27:00.803Z"
  },
  {
    "id": 1769855771159,
    "itemType": "Cakes",
    "product": "Vanilla Cake",
    "quantity": 2,
    "unitPrice": 300,
    "total": 600,
    "saleType": "Counter Sale",
    "paymentMode": "Cash",
    "status": "Completed",
    "addedBy": "sam12",
    "business": "MA-2818",
    "date": "2026-01-31T10:36:11.159Z"
  },
  {
    "id": 1769855806806,
    "itemType": "Pastries and Desserts",
    "product": "Swiss Roll",
    "quantity": 3,
    "unitPrice": 35,
    "total": 105,
    "saleType": "Counter Sale",
    "paymentMode": "UPI",
    "status": "Completed",
    "addedBy": "sam12",
    "business": "MA-2818",
    "date": "2026-01-31T10:36:46.806Z"
  },
  {
    "id": 1769857784849,
    "itemType": "Savory Veg Items",
    "product": "Paneer Puff",
    "quantity": 5,
    "unitPrice": 50,
    "total": 250,
    "saleType": "Counter Sale",
    "paymentMode": "Cash",
    "status": "Completed",
    "addedBy": "sam12",
    "business": "MA-2818",
    "date": "2026-01-31T11:09:44.849Z"
  },
  {
    "id": 1769857823609,
    "itemType": "Cookies and Tea Time",
    "product": "Butter Cookies",
    "quantity": 10,
    "unitPrice": 10,
    "total": 100,
    "saleType": "Counter Sale",
    "paymentMode": "Cash",
    "status": "Completed",
    "addedBy": "sam12",
    "business": "MA-2818",
    "date": "2026-01-31T11:10:23.609Z"
  },
  {
    "id": 1769870684732,
    "itemType": "Cakes",
    "product": "Vanilla Cake",
    "quantity": 3,
    "unitPrice": 650,
    "total": 1950,
    "saleType": "Counter Sale",
    "paymentMode": "Cash",
    "status": "Completed",
    "addedBy": "sam12",
    "business": "MA-2818",
    "date": "2026-01-31T14:44:44.732Z"
  },
  {
    "id": 1769870712631,
    "itemType": "Pastries and Desserts",
    "product": "Strawberry Pastry",
    "quantity": 8,
    "unitPrice": 120,
    "total": 960,
    "saleType": "Counter Sale",
    "paymentMode": "Cash",
    "status": "Completed",
    "addedBy": "sam12",
    "business": "MA-2818",
    "date": "2026-01-31T14:45:12.631Z"
  },
  {
    "id": 1769870735977,
    "itemType": "Savory Veg Items",
    "product": "Paneer Puff",
    "quantity": 15,
    "unitPrice": 70,
    "total": 1050,
    "saleType": "Counter Sale",
    "paymentMode": "Cash",
    "status": "Completed",
    "addedBy": "sam12",
    "business": "MA-2818",
    "date": "2026-01-31T14:45:35.977Z"
  },
  {
    "id": 1769870761577,
    "itemType": "Cookies and Tea Time",
    "product": "Butter Cookies",
    "quantity": 20,
    "unitPrice": 20,
    "total": 400,
    "saleType": "Counter Sale",
    "paymentMode": "Cash",
    "status": "Completed",
    "addedBy": "sam12",
    "business": "MA-2818",
    "date": "2026-01-31T14:46:01.577Z"
  },
  {
    "id": 1769871823743,
    "itemType": "Savory Veg Items",
    "product": "Cheese Croissant",
    "quantity": 15,
    "unitPrice": 80,
    "total": 1200,
    "saleType": "Counter Sale",
    "paymentMode": "Cash",
    "status": "Completed",
    "addedBy": "sam12",
    "business": "MA-2818",
    "date": "2026-01-31T15:03:43.743Z"
  },
  {
    "id": 1769930423932,
    "itemType": "Cakes",
    "product": "Vanilla Cake",
    "quantity": 5,
    "unitPrice": 450,
    "total": 2250,
    "saleType": "Counter Sale",
    "paymentMode": "Cash",
    "status": "Completed",
    "addedBy": "sam12",
    "business": "MA-2818",
    "date": "2026-02-01T07:20:23.932Z"
  },
  {
    "id": 1769956593015,
    "itemType": "Cakes",
    "product": "Red Velvet Cake",
    "quantity": 8,
    "unitPrice": 750,
    "total": 6000,
    "saleType": "Counter Sale",
    "paymentMode": "UPI",
    "status": "Completed",
    "addedBy": "sam12",
    "business": "MA-2818",
    "date": "2026-02-01T14:36:33.015Z"
  },
  {
    "id": 1769956649404,
    "itemType": "Pastries and Desserts",
    "product": "Cupcake",
    "quantity": 9,
    "unitPrice": 40,
    "total": 360,
    "saleType": "Counter Sale",
    "paymentMode": "Cash",
    "status": "Completed",
    "addedBy": "sam12",
    "business": "MA-2818",
    "date": "2026-02-01T14:37:29.404Z"
  },
  {
    "id": 1769956671614,
    "itemType": "Pastries and Desserts",
    "product": "Chocolate Cupcake",
    "quantity": 10,
    "unitPrice": 50,
    "total": 500,
    "saleType": "Counter Sale",
    "paymentMode": "Cash",
    "status": "Completed",
    "addedBy": "sam12",
    "business": "MA-2818",
    "date": "2026-02-01T14:37:51.614Z"
  },
  {
    "id": 1769956694432,
    "itemType": "Breads and Buns",
    "product": "Whole Wheat Bread",
    "quantity": 8,
    "unitPrice": 70,
    "total": 560,
    "saleType": "Online Order",
    "paymentMode": "UPI",
    "status": "Completed",
    "addedBy": "sam12",
    "business": "MA-2818",
    "date": "2026-02-01T14:38:14.432Z"
  },
  {
    "id": 1769956731879,
    "itemType": "Savory Veg Items",
    "product": "Veg Samosa",
    "quantity": 60,
    "unitPrice": 30,
    "total": 1800,
    "saleType": "Bulk Order",
    "paymentMode": "Card",
    "status": "Completed",
    "addedBy": "sam12",
    "business": "MA-2818",
    "date": "2026-02-01T14:38:51.879Z"
  },
  {
    "id": 1769956787371,
    "itemType": "Breads and Buns",
    "product": "Burger Buns",
    "quantity": 40,
    "unitPrice": 90,
    "total": 3600,
    "saleType": "Counter Sale",
    "paymentMode": "UPI",
    "status": "Completed",
    "addedBy": "sam12",
    "business": "MA-2818",
    "date": "2026-02-01T14:39:47.371Z"
  },
  {
    "id": 1769956810507,
    "itemType": "Cookies and Tea Time",
    "product": "Butter Cookies",
    "quantity": 10,
    "unitPrice": 60,
    "total": 600,
    "saleType": "Counter Sale",
    "paymentMode": "Cash",
    "status": "Completed",
    "addedBy": "sam12",
    "business": "MA-2818",
    "date": "2026-02-01T14:40:10.507Z"
  },
  {
    "id": 1769956835260,
    "itemType": "Pastries and Desserts",
    "product": "Swiss Roll",
    "quantity": 20,
    "unitPrice": 80,
    "total": 1600,
    "saleType": "Counter Sale",
    "paymentMode": "Cash",
    "status": "Completed",
    "addedBy": "sam12",
    "business": "MA-2818",
    "date": "2026-02-01T14:40:35.260Z"
  },
  {
    "id": 1769957227077,
    "itemType": "Cakes",
    "product": "Vanilla Cake",
    "quantity": 2,
    "unitPrice": 400,
    "total": 800,
    "saleType": "Online Order",
    "paymentMode": "UPI",
    "status": "Completed",
    "addedBy": "sam12",
    "business": "MA-2818",
    "date": "2026-02-01T14:47:07.077Z"
  }
]